ssmcommander/__init__.py
ssmcommander/cli.py
ssmcommander/tree.py
ssmcommander/yaml_parser.py
ssmcommander/tests/__init__.py
ssmcommander/tests/test_ssmcommander.py
aws_ssm_commander-0.0.4.dist-info/LICENSE
aws_ssm_commander-0.0.4.dist-info/METADATA
aws_ssm_commander-0.0.4.dist-info/WHEEL
aws_ssm_commander-0.0.4.dist-info/entry_points.txt
aws_ssm_commander-0.0.4.dist-info/top_level.txt
aws_ssm_commander-0.0.4.dist-info/RECORD
