Metadata-Version: 2.1
Name: aws-ssm-commander
Version: 0.0.4
Summary: A utility for dealing with AWS SSM Parameter Store
Home-page: https://github.com/djcrabhat/aws-ssm-commander
License: UNKNOWN
Platform: UNKNOWN
Requires-Dist: Click
Requires-Dist: boto3
Requires-Dist: pyyaml
Requires-Dist: treelib
